{
  "name": "Tugas 2_IAP",
  "nodes": [
    {
      "parameters": {
        "formTitle": "Generate Gambar Konten Otomatis",
        "formDescription": "isi informasi dibawah ini untuk memulai proses generate gambar",
        "formFields": {
          "values": [
            {
              "fieldLabel": "prompt",
              "fieldName": "prompt"
            },
            {
              "fieldLabel": "img_url",
              "fieldName": "img_url"
            },
            {
              "fieldLabel": "task_type",
              "fieldName": "task_type",
              "placeholder": "mj_txt2img"
            },
            {
              "fieldLabel": "api_key",
              "fieldType": "textarea",
              "fieldName": "api_key"
            }
          ]
        },
        "options": {}
      },
      "type": "n8n-nodes-base.formTrigger",
      "typeVersion": 2.5,
      "position": [
        0,
        0
      ],
      "id": "26d5ed22-985e-4626-ba8e-e0f3c8880b92",
      "name": "On form submission",
      "webhookId": "faa7921d-a0ae-433b-b890-668faf3b80fb"
    },
    {
      "parameters": {
        "conditions": {
          "options": {
            "caseSensitive": true,
            "leftValue": "",
            "typeValidation": "loose",
            "version": 3
          },
          "conditions": [
            {
              "id": "d6e6c791-0789-4185-9a63-0f9032d778f4",
              "leftValue": "success",
              "rightValue": "={{$json.data.state}}",
              "operator": {
                "type": "string",
                "operation": "equals",
                "name": "filter.operator.equals"
              }
            }
          ],
          "combinator": "and"
        },
        "looseTypeValidation": true,
        "options": {}
      },
      "type": "n8n-nodes-base.if",
      "typeVersion": 2.3,
      "position": [
        832,
        0
      ],
      "id": "9640e636-52b3-44e6-9a87-62f25533c2c7",
      "name": "If"
    },
    {
      "parameters": {
        "jsCode": "const result = JSON.parse($json.data.resultJson);\n\nreturn [{\n  img1: result.resultUrls[0] || null,\n  img2: result.resultUrls[1] || null,\n  img3: result.resultUrls[2] || null,\n  img4: result.resultUrls[3] || null\n}];\n"
      },
      "type": "n8n-nodes-base.code",
      "typeVersion": 2,
      "position": [
        1072,
        -16
      ],
      "id": "64e76136-4ec6-46f2-8d7f-4c5d18cc1abd",
      "name": "Code in JavaScript"
    },
    {
      "parameters": {
        "jsCode": "const urls = [\n  $json.img1,\n  $json.img2,\n  $json.img3,\n  $json.img4\n].filter(Boolean);\n\n// jadikan 1 URL = 1 item\nreturn urls.map((url, index) => ({\n  json: {\n    url,\n    index: index + 1\n  }\n}));"
      },
      "type": "n8n-nodes-base.code",
      "typeVersion": 2,
      "position": [
        1280,
        -16
      ],
      "id": "d4c48c64-470f-403a-bc88-298e2ad1232e",
      "name": "Code in JavaScript1"
    },
    {
      "parameters": {
        "url": "={{ $json.url }}",
        "options": {
          "response": {
            "response": {
              "responseFormat": "file"
            }
          }
        }
      },
      "type": "n8n-nodes-base.httpRequest",
      "typeVersion": 4.4,
      "position": [
        1488,
        -16
      ],
      "id": "0af37f20-7707-4c85-be7c-19b08a9bf697",
      "name": "HTTP Request2"
    },
    {
      "parameters": {
        "operation": "sendPhoto",
        "chatId": "6092872465",
        "binaryData": true,
        "additionalFields": {}
      },
      "type": "n8n-nodes-base.telegram",
      "typeVersion": 1.2,
      "position": [
        1680,
        -16
      ],
      "id": "5d3ad590-43d7-4b28-a0de-d0c59f19c66e",
      "name": "Send a photo message",
      "webhookId": "b587db70-3556-4612-afe5-de59848a9e5b",
      "credentials": {
        "telegramApi": {
          "id": "wj6IklY82GRlAQMm",
          "name": "Telegram account 2"
        }
      }
    },
    {
      "parameters": {
        "method": "POST",
        "url": "https://api.kie.ai/api/v1/jobs/createTask",
        "sendHeaders": true,
        "headerParameters": {
          "parameters": [
            {
              "name": "Content-Type",
              "value": "application/json"
            },
            {
              "name": "Authorization",
              "value": "=Bearer {{ $json.api_key }}"
            }
          ]
        },
        "sendBody": true,
        "specifyBody": "json",
        "jsonBody": "={\n  \"model\": \"grok-imagine/text-to-image\",\n  \"input\": {\n    \"prompt\": \"{{$json.prompt}}\",\n    \"aspect_ratio\": \"3:2\"\n  }\n}",
        "options": {}
      },
      "type": "n8n-nodes-base.httpRequest",
      "typeVersion": 4.4,
      "position": [
        208,
        0
      ],
      "id": "134b9ec9-4698-4728-b8cf-4258dc7f1f99",
      "name": "Mengirim Image Generation Request ke KIE.AI API"
    },
    {
      "parameters": {
        "amount": 10
      },
      "type": "n8n-nodes-base.wait",
      "typeVersion": 1.1,
      "position": [
        416,
        0
      ],
      "id": "df7a6232-a63a-431e-9e81-6bcb98204740",
      "name": "Menunggu Proses Generate Gambar",
      "webhookId": "161d2d56-dac2-4600-8509-058c3528b104"
    },
    {
      "parameters": {
        "url": "https://api.kie.ai/api/v1/jobs/recordInfo",
        "sendQuery": true,
        "queryParameters": {
          "parameters": [
            {
              "name": "taskId",
              "value": "={{ $json.data.taskId }}"
            }
          ]
        },
        "sendHeaders": true,
        "headerParameters": {
          "parameters": [
            {
              "name": "Content-Type",
              "value": "application/json"
            },
            {
              "name": "Authorization",
              "value": "=Bearer {{$node[\"On form submission\"].json[\"api_key\"]}}"
            }
          ]
        },
        "options": {}
      },
      "type": "n8n-nodes-base.httpRequest",
      "typeVersion": 4.4,
      "position": [
        624,
        0
      ],
      "id": "94011a74-2847-4f80-900f-3c27f209e073",
      "name": "Mendapatkan Status Generate"
    }
  ],
  "pinData": {},
  "connections": {
    "On form submission": {
      "main": [
        [
          {
            "node": "Mengirim Image Generation Request ke KIE.AI API",
            "type": "main",
            "index": 0
          }
        ]
      ]
    },
    "If": {
      "main": [
        [
          {
            "node": "Code in JavaScript",
            "type": "main",
            "index": 0
          }
        ],
        [
          {
            "node": "Menunggu Proses Generate Gambar",
            "type": "main",
            "index": 0
          }
        ]
      ]
    },
    "Code in JavaScript": {
      "main": [
        [
          {
            "node": "Code in JavaScript1",
            "type": "main",
            "index": 0
          }
        ]
      ]
    },
    "Code in JavaScript1": {
      "main": [
        [
          {
            "node": "HTTP Request2",
            "type": "main",
            "index": 0
          }
        ]
      ]
    },
    "HTTP Request2": {
      "main": [
        [
          {
            "node": "Send a photo message",
            "type": "main",
            "index": 0
          }
        ]
      ]
    },
    "Mengirim Image Generation Request ke KIE.AI API": {
      "main": [
        [
          {
            "node": "Menunggu Proses Generate Gambar",
            "type": "main",
            "index": 0
          }
        ]
      ]
    },
    "Menunggu Proses Generate Gambar": {
      "main": [
        [
          {
            "node": "Mendapatkan Status Generate",
            "type": "main",
            "index": 0
          }
        ]
      ]
    },
    "Mendapatkan Status Generate": {
      "main": [
        [
          {
            "node": "If",
            "type": "main",
            "index": 0
          }
        ]
      ]
    }
  },
  "active": true,
  "settings": {
    "executionOrder": "v1",
    "binaryMode": "separate",
    "availableInMCP": false
  },
  "versionId": "76a17ecb-3887-4f45-aeae-b9cfefa6147f",
  "meta": {
    "templateCredsSetupCompleted": true,
    "instanceId": "f0ce829ce71044abcecbf09417e4a9c6d178f874d34c47f0e6cb4e665542834c"
  },
  "id": "eO3JW12rtrFmYq18",
  "tags": []
}